CompassAI
