Metadata-Version: 2.1
Name: CompassAI
Version: 0.0.3
Summary: For evaluating trained model by bootstrapping test set, assessing fairness, and model card
Home-page: https://github.com/optum-labs/CompassAI
Author: Jirapat Samranvedhya
Author-email: jirapat.samranvedhya@optum.com
License: MIT
Platform: UNKNOWN
